arquee/__init__.py
arquee/cli.py
arquee/config.py
arquee/utils.py
arquee/server/__init__.py
arquee/server/server.py
arquee/server/server_db.py
arquee/tools/__init__.py
arquee/tools/db.py
arquee/tools/environment.py
arquee/tools/worker.py
arquee-0.10.dist-info/METADATA
arquee-0.10.dist-info/WHEEL
arquee-0.10.dist-info/entry_points.txt
arquee-0.10.dist-info/top_level.txt
arquee-0.10.dist-info/RECORD
