Metadata-Version: 2.4
Name: arquee
Version: 0.10
Summary: Add your description here
Requires-Python: >=3.10
Requires-Dist: flask>=3.1.0
Requires-Dist: pyspark>=3.5.5
Requires-Dist: python-dotenv>=1.1.0
Requires-Dist: waitress>=3.0.2
